_generics_version.py
generics/__init__.py
generics/py.typed
python_generics-0.2.4.dist-info/METADATA
python_generics-0.2.4.dist-info/WHEEL
python_generics-0.2.4.dist-info/licenses/LICENSE
python_generics-0.2.4.dist-info/RECORD
