Metadata-Version: 2.4
Name: python-generics
Version: 0.2.4
Summary: A package to determine the values of generic classes through instances or subclasses 
Project-URL: Changelog, https://github.com/Hochfrequenz/python-generics/releases
Project-URL: Homepage, https://github.com/Hochfrequenz/python-generics
Author-email: Hochfrequenz Unternehmensberatung GmbH <info@hochfrequenz.de>
License: MIT
License-File: LICENSE
Keywords: generics,python
Classifier: Development Status :: 4 - Beta
Classifier: Environment :: Console
Classifier: Intended Audience :: Developers
Classifier: License :: OSI Approved :: MIT License
Classifier: Operating System :: OS Independent
Classifier: Programming Language :: Python
Classifier: Programming Language :: Python :: 3 :: Only
Classifier: Programming Language :: Python :: 3.10
Classifier: Programming Language :: Python :: 3.11
Classifier: Programming Language :: Python :: 3.12
Classifier: Programming Language :: Python :: 3.13
Classifier: Programming Language :: Python :: 3.14
Requires-Python: >=3.10
Provides-Extra: coverage
Requires-Dist: coverage==7.10.7; extra == 'coverage'
Provides-Extra: formatting
Requires-Dist: black==25.9.0; extra == 'formatting'
Requires-Dist: isort==6.1.0; extra == 'formatting'
Provides-Extra: linting
Requires-Dist: pylint==3.3.9; extra == 'linting'
Provides-Extra: spellcheck
Requires-Dist: codespell==2.4.1; extra == 'spellcheck'
Provides-Extra: test-packaging
Requires-Dist: build==1.3.0; extra == 'test-packaging'
Requires-Dist: twine==6.2.0; extra == 'test-packaging'
Provides-Extra: tests
Requires-Dist: pydantic==2.12.3; extra == 'tests'
Requires-Dist: pytest==8.4.2; extra == 'tests'
Provides-Extra: type-check
Requires-Dist: mypy==1.18.2; extra == 'type-check'
